<?xml version="1.0" encoding="UTF-8" ?><tv date="20260405">
<channel id="TVSClassicSports.us@SD"><display-name>TVS Classic Sports</display-name><icon src="https://i.imgur.com/auR0Mi6.png"/><url>https://watchyour.tv</url></channel>
<channel id="TVSBoxing.us@SD"><display-name>TVS Boxing Network</display-name><icon src="https://i.imgur.com/30ZoF75.png"/><url>https://watchyour.tv</url></channel>
<channel id="TVSTavern.us@SD"><display-name>TVS Tavern TV</display-name><icon src="https://i.imgur.com/3GTIs4j.png"/><url>https://watchyour.tv</url></channel>
<channel id="TVSMainstreet.us@SD"><display-name>TVS Main Street</display-name><icon src="https://i.imgur.com/N9nQpnP.png"/><url>https://watchyour.tv</url></channel>
<channel id="TVSWomenSports.us@SD"><display-name>TVS Women&apos;s Sports Network</display-name><icon src="https://i.imgur.com/8hC4PfF.png"/><url>https://watchyour.tv</url></channel>
<channel id="TVSTurbo.us@SD"><display-name>TVS Turbo Network</display-name><icon src="https://i.imgur.com/7zYIbU1.png"/><url>https://watchyour.tv</url></channel>
<channel id="TVSNostalgia.us@SD"><display-name>TVS Nostalgia</display-name><icon src="https://i.imgur.com/q72FCCQ.png"/><url>https://watchyour.tv</url></channel>
<channel id="796"><display-name>TVS All American</display-name><url>https://watchyour.tv</url></channel>
<channel id="802"><display-name>TVS Buckboard Network</display-name><url>https://watchyour.tv</url></channel>
<channel id="TVSCipherNetwork.us@SD"><display-name>TVS Cipher Network</display-name><icon src="https://i.imgur.com/yyz1S2W.png"/><url>https://watchyour.tv</url></channel>
<channel id="TVSFilmNoirNetwork.us@SD"><display-name>TVS Film Noir Network</display-name><icon src="https://i.imgur.com/A4yWhQw.png"/><url>https://watchyour.tv</url></channel>
<channel id="TVSTodayHomeEntertainmentNetwork.us@SD"><display-name>TVS Today Home Entertainment Network</display-name><url>https://watchyour.tv</url></channel>
<channel id="840"><display-name>TVS Consumer Direct</display-name><url>https://watchyour.tv</url></channel>
<channel id="TVSPinballNetwork.us@SD"><display-name>TVS Pinball Network</display-name><icon src="https://i.imgur.com/HHmc14i.png"/><url>https://watchyour.tv</url></channel>
<channel id="834"><display-name>Pet Parade Network</display-name><url>https://watchyour.tv</url></channel>
<channel id="833"><display-name>TVS Bowling Network</display-name><url>https://watchyour.tv</url></channel>
<channel id="832"><display-name>TVS TeleSports</display-name><url>https://watchyour.tv</url></channel>
<channel id="831"><display-name>TVS Action Network</display-name><url>https://watchyour.tv</url></channel>
<channel id="TVSQuizShowNetwork.us@SD"><display-name>TVS Quiz Show Network</display-name><icon src="https://i.imgur.com/5ljQwx2.png"/><url>https://watchyour.tv</url></channel>
<channel id="TVSComedyNetwork.us@SD"><display-name>TVS Comedy</display-name><icon src="https://i.imgur.com/rXORbti.png"/><url>https://watchyour.tv</url></channel>
<channel id="TVSSelectNetwork.us@SD"><display-name>TVS Select Network</display-name><url>https://watchyour.tv</url></channel>
<channel id="TVSTallyHo.us@SD"><display-name>TVS Tally Ho</display-name><icon src="https://i.imgur.com/JlFwnDD.png"/><url>https://watchyour.tv</url></channel>
<channel id="TVSHorrorNetwork.us@SD"><display-name>TVS Horror</display-name><icon src="https://i.imgur.com/n0LAunC.png"/><url>https://watchyour.tv</url></channel>
<channel id="824"><display-name>TVS Port O Call</display-name><url>https://watchyour.tv</url></channel>
<channel id="TVSHollywoodHistory.us@SD"><display-name>TVS Hollywood History</display-name><icon src="https://i.imgur.com/QtQGyMS.png"/><url>https://watchyour.tv</url></channel>
<channel id="TVSNostalgiaMovies.us@SD"><display-name>TVS Nostalgia Movie Network</display-name><icon src="https://i.imgur.com/w4fxiKi.png"/><url>https://watchyour.tv</url></channel>
<channel id="TVSWesternMovie.us@SD"><display-name>TVS Western Movie</display-name><icon src="https://i.imgur.com/dwr98qb.png"/><url>https://watchyour.tv</url></channel>
<channel id="TVSClassicMovies.us@SD"><display-name>TVS Classic Movies</display-name><icon src="https://i.imgur.com/st1xMsw.png"/><url>https://watchyour.tv</url></channel>
<channel id="TVSDriveInMovie.us@SD"><display-name>TVS Drive In Movie</display-name><icon src="https://i.imgur.com/OR9APjb.png"/><url>https://watchyour.tv</url></channel>
<channel id="818"><display-name>TVS Tel Ra Network</display-name><url>https://watchyour.tv</url></channel>
<channel id="817"><display-name>TVS Light Network</display-name><url>https://watchyour.tv</url></channel>
<channel id="TVSHiTops.us@SD"><display-name>TVS Hi Tops</display-name><icon src="https://i.imgur.com/RiWg1IA.png"/><url>https://watchyour.tv</url></channel>
<channel id="815"><display-name>TVS Flashback Network</display-name><url>https://watchyour.tv</url></channel>
<channel id="845"><display-name>TVS Opus Network</display-name><url>https://watchyour.tv</url></channel>
<channel id="850"><display-name>TVS Soft Winds Network</display-name><url>https://watchyour.tv</url></channel>
<channel id="849"><display-name>TVS Vintage Network</display-name><url>https://watchyour.tv</url></channel>
<channel id="848"><display-name>TVS Variety Network</display-name><url>https://watchyour.tv</url></channel>
<channel id="TVSSiloDiscountNetwork.us@SD"><display-name>TVS Sci Fi Network</display-name><url>https://watchyour.tv</url></channel>
<channel id="846"><display-name>TVS Talk Network</display-name><url>https://watchyour.tv</url></channel>
<channel id="TVSFrontPageDetective.us@SD"><display-name>TVS Front Page Detective</display-name><icon src="https://i.imgur.com/1YHIbZB.png"/><url>https://watchyour.tv</url></channel>
<programme start="20260405003909 +0000" stop="20260405013709 +0000" channel="796"><title lang="en">teleup-event_1679252400_3600</title><category lang="en">Sports</category></programme>
<programme start="20260405013657 +0000" stop="20260405023157 +0000" channel="796"><title lang="en">teleup-event_1679256000_3600</title><category lang="en">Sports</category></programme>
<programme start="20260405023154 +0000" stop="20260405032454 +0000" channel="796"><title lang="en">teleup-event_1679259600_3150</title><category lang="en">Sports</category></programme>
<programme start="20260405032450 +0000" stop="20260405034850 +0000" channel="796"><title lang="en">teleup-event_1679228983_1409</title><category lang="en">Sports</category></programme>
<programme start="20260405034819 +0000" stop="20260405040019 +0000" channel="796"><title lang="en">teleup-event_1679240408_3176</title><category lang="en">Sports</category></programme>
<programme start="20260405003909 +0000" stop="20260405013709 +0000" channel="802"><title lang="en">teleup-event_1679252400_3600</title><category lang="en">TV Classics</category></programme>
<programme start="20260405013657 +0000" stop="20260405023157 +0000" channel="802"><title lang="en">teleup-event_1679256000_3600</title><category lang="en">TV Classics</category></programme>
<programme start="20260405023154 +0000" stop="20260405032454 +0000" channel="802"><title lang="en">teleup-event_1679259600_3150</title><category lang="en">TV Classics</category></programme>
<programme start="20260405032450 +0000" stop="20260405034850 +0000" channel="802"><title lang="en">teleup-event_1679228983_1409</title><category lang="en">TV Classics</category></programme>
<programme start="20260405034819 +0000" stop="20260405040019 +0000" channel="802"><title lang="en">teleup-event_1679240408_3176</title><category lang="en">TV Classics</category></programme>
<programme start="20260405003909 +0000" stop="20260405013709 +0000" channel="815"><title lang="en">teleup-event_1679252400_3600</title><category lang="en">TV Classics</category></programme>
<programme start="20260405013657 +0000" stop="20260405023157 +0000" channel="815"><title lang="en">teleup-event_1679256000_3600</title><category lang="en">TV Classics</category></programme>
<programme start="20260405023154 +0000" stop="20260405032454 +0000" channel="815"><title lang="en">teleup-event_1679259600_3150</title><category lang="en">TV Classics</category></programme>
<programme start="20260405032450 +0000" stop="20260405034850 +0000" channel="815"><title lang="en">teleup-event_1679228983_1409</title><category lang="en">TV Classics</category></programme>
<programme start="20260405034819 +0000" stop="20260405040019 +0000" channel="815"><title lang="en">teleup-event_1679240408_3176</title><category lang="en">TV Classics</category></programme>
<programme start="20260405001052 +0000" stop="20260405003452 +0000" channel="817"><title lang="en">Shirley Temple In The Little Princess Part 3</title><category lang="en">Kids &amp; Family</category></programme>
<programme start="20260405003452 +0000" stop="20260405003752 +0000" channel="817"><title lang="en">Here Comes My Baby 1-encoded3-encoded2</title><category lang="en">Kids &amp; Family</category></programme>
<programme start="20260405003744 +0000" stop="20260405005844 +0000" channel="817"><title lang="en">Shirley Temple In The Little Princess Part 4</title><category lang="en">Kids &amp; Family</category></programme>
<programme start="20260405005844 +0000" stop="20260405022444 +0000" channel="817"><title lang="en">Benji (1974)</title><category lang="en">Kids &amp; Family</category></programme>
<programme start="20260405022444 +0000" stop="20260405022744 +0000" channel="817"><title lang="en">confidential 1-encoded2</title><category lang="en">Kids &amp; Family</category></programme>
<programme start="20260405022726 +0000" stop="20260405025226 +0000" channel="817"><title lang="en">The Smith Family</title><category lang="en">Kids &amp; Family</category></programme>
<programme start="20260405025218 +0000" stop="20260405031718 +0000" channel="817"><title lang="en">The Smith Family</title><category lang="en">Kids &amp; Family</category></programme>
<programme start="20260405031657 +0000" stop="20260405040057 +0000" channel="817"><title lang="en">Baker&apos;s Hawk (1976)</title><category lang="en">Kids &amp; Family</category></programme>
<programme start="20260405002018 +0000" stop="20260405013518 +0000" channel="818"><title lang="en">McMillan &amp; Wife 107</title><category lang="en">Mixed Programming</category></programme>
<programme start="20260405013442 +0000" stop="20260405023842 +0000" channel="818"><title lang="en">wrestling3</title><category lang="en">Mixed Programming</category></programme>
<programme start="20260405023826 +0000" stop="20260405024126 +0000" channel="818"><title lang="en">Rockin Robin-encoded2</title><category lang="en">Mixed Programming</category></programme>
<programme start="20260405024104 +0000" stop="20260405030404 +0000" channel="818"><title lang="en">Joan Rivers 7</title><category lang="en">Mixed Programming</category></programme>
<programme start="20260405030350 +0000" stop="20260405033550 +0000" channel="818"><title lang="en">bloopertoons-encoded2</title><category lang="en">Mixed Programming</category></programme>
<programme start="20260405033457 +0000" stop="20260405035657 +0000" channel="818"><title lang="en">Mari S01e02r - Laila Ali &amp; High Five</title><category lang="en">Mixed Programming</category></programme>
<programme start="20260405035606 +0000" stop="20260405040006 +0000" channel="818"><title lang="en">Lake Tahoe Segment 1</title><category lang="en">Mixed Programming</category></programme>
<programme start="20260405003909 +0000" stop="20260405013709 +0000" channel="824"><title lang="en">teleup-event_1679252400_3600</title><category lang="en">Entertainment</category></programme>
<programme start="20260405013657 +0000" stop="20260405023157 +0000" channel="824"><title lang="en">teleup-event_1679256000_3600</title><category lang="en">Entertainment</category></programme>
<programme start="20260405023154 +0000" stop="20260405032454 +0000" channel="824"><title lang="en">teleup-event_1679259600_3150</title><category lang="en">Entertainment</category></programme>
<programme start="20260405032450 +0000" stop="20260405034850 +0000" channel="824"><title lang="en">teleup-event_1679228983_1409</title><category lang="en">Entertainment</category></programme>
<programme start="20260405034819 +0000" stop="20260405040019 +0000" channel="824"><title lang="en">teleup-event_1679240408_3176</title><category lang="en">Entertainment</category></programme>
<programme start="20260405003909 +0000" stop="20260405013709 +0000" channel="831"><title lang="en">teleup-event_1679252400_3600</title><category lang="en">Entertainment</category></programme>
<programme start="20260405013657 +0000" stop="20260405023157 +0000" channel="831"><title lang="en">teleup-event_1679256000_3600</title><category lang="en">Entertainment</category></programme>
<programme start="20260405023154 +0000" stop="20260405032454 +0000" channel="831"><title lang="en">teleup-event_1679259600_3150</title><category lang="en">Entertainment</category></programme>
<programme start="20260405032450 +0000" stop="20260405034850 +0000" channel="831"><title lang="en">teleup-event_1679228983_1409</title><category lang="en">Entertainment</category></programme>
<programme start="20260405034819 +0000" stop="20260405040019 +0000" channel="831"><title lang="en">teleup-event_1679240408_3176</title><category lang="en">Entertainment</category></programme>
<programme start="20260405003909 +0000" stop="20260405013709 +0000" channel="832"><title lang="en">teleup-event_1679252400_3600</title><category lang="en">Sports</category></programme>
<programme start="20260405013657 +0000" stop="20260405023157 +0000" channel="832"><title lang="en">teleup-event_1679256000_3600</title><category lang="en">Sports</category></programme>
<programme start="20260405023154 +0000" stop="20260405032454 +0000" channel="832"><title lang="en">teleup-event_1679259600_3150</title><category lang="en">Sports</category></programme>
<programme start="20260405032450 +0000" stop="20260405034850 +0000" channel="832"><title lang="en">teleup-event_1679228983_1409</title><category lang="en">Sports</category></programme>
<programme start="20260405034819 +0000" stop="20260405040019 +0000" channel="832"><title lang="en">teleup-event_1679240408_3176</title><category lang="en">Sports</category></programme>
<programme start="20260405003909 +0000" stop="20260405013709 +0000" channel="833"><title lang="en">teleup-event_1679252400_3600</title><category lang="en">Sports</category></programme>
<programme start="20260405013657 +0000" stop="20260405023157 +0000" channel="833"><title lang="en">teleup-event_1679256000_3600</title><category lang="en">Sports</category></programme>
<programme start="20260405023154 +0000" stop="20260405032454 +0000" channel="833"><title lang="en">teleup-event_1679259600_3150</title><category lang="en">Sports</category></programme>
<programme start="20260405032450 +0000" stop="20260405034850 +0000" channel="833"><title lang="en">teleup-event_1679228983_1409</title><category lang="en">Sports</category></programme>
<programme start="20260405034819 +0000" stop="20260405040019 +0000" channel="833"><title lang="en">teleup-event_1679240408_3176</title><category lang="en">Sports</category></programme>
<programme start="20260405003909 +0000" stop="20260405013709 +0000" channel="834"><title lang="en">teleup-event_1679252400_3600</title><category lang="en">Kids &amp; Family</category></programme>
<programme start="20260405013657 +0000" stop="20260405023157 +0000" channel="834"><title lang="en">teleup-event_1679256000_3600</title><category lang="en">Kids &amp; Family</category></programme>
<programme start="20260405023154 +0000" stop="20260405032454 +0000" channel="834"><title lang="en">teleup-event_1679259600_3150</title><category lang="en">Kids &amp; Family</category></programme>
<programme start="20260405032450 +0000" stop="20260405034850 +0000" channel="834"><title lang="en">teleup-event_1679228983_1409</title><category lang="en">Kids &amp; Family</category></programme>
<programme start="20260405034819 +0000" stop="20260405040019 +0000" channel="834"><title lang="en">teleup-event_1679240408_3176</title><category lang="en">Kids &amp; Family</category></programme>
<programme start="20260405005316 +0000" stop="20260405012216 +0000" channel="840"><title lang="en">Little Giant Ladder</title><category lang="en">Home Shopping</category></programme>
<programme start="20260405012156 +0000" stop="20260405015256 +0000" channel="840"><title lang="en">Ninja Foodi Grill (800) 383-35 97</title><category lang="en">Home Shopping</category></programme>
<programme start="20260405015158 +0000" stop="20260405022158 +0000" channel="840"><title lang="en">Austin City Limits (800) 948-3405</title><category lang="en">Home Shopping</category></programme>
<programme start="20260405022100 +0000" stop="20260405040000 +0000" channel="840"><title lang="en">Rare Collectibles</title><category lang="en">Home Shopping</category></programme>
<programme start="20260405003509 +0000" stop="20260405010709 +0000" channel="845"><title lang="en">Shindig with The Beatles (1964)</title><category lang="en">Featured</category></programme>
<programme start="20260405010644 +0000" stop="20260405015744 +0000" channel="845"><title lang="en">Hollywood Palace S02E12 with Burl Ives</title><category lang="en">Featured</category></programme>
<programme start="20260405015716 +0000" stop="20260405025816 +0000" channel="845"><title lang="en">Hollywood Palace S2E20 with George Burns</title><category lang="en">Featured</category></programme>
<programme start="20260405025805 +0000" stop="20260405035805 +0000" channel="845"><title lang="en">Hollywood Palace S01E10 with Dean Martin</title><category lang="en">Featured</category></programme>
<programme start="20260405035712 +0000" stop="20260405040012 +0000" channel="845"><title lang="en">SugarSlightshow-encoded2</title><category lang="en">Featured</category></programme>
<programme start="20260405035958 +0000" stop="20260405040058 +0000" channel="845"><category lang="en">Featured</category></programme>
<programme start="20260405003909 +0000" stop="20260405013709 +0000" channel="846"><title lang="en">teleup-event_1679252400_3600</title><category lang="en">Mixed Programming</category></programme>
<programme start="20260405013657 +0000" stop="20260405023157 +0000" channel="846"><title lang="en">teleup-event_1679256000_3600</title><category lang="en">Mixed Programming</category></programme>
<programme start="20260405023154 +0000" stop="20260405032454 +0000" channel="846"><title lang="en">teleup-event_1679259600_3150</title><category lang="en">Mixed Programming</category></programme>
<programme start="20260405032450 +0000" stop="20260405034850 +0000" channel="846"><title lang="en">teleup-event_1679228983_1409</title><category lang="en">Mixed Programming</category></programme>
<programme start="20260405034819 +0000" stop="20260405040019 +0000" channel="846"><title lang="en">teleup-event_1679240408_3176</title><category lang="en">Mixed Programming</category></programme>
<programme start="20260405004331 +0000" stop="20260405004731 +0000" channel="848"><title lang="en">i lcan help-encoded2</title><category lang="en">Entertainment</category></programme>
<programme start="20260405004647 +0000" stop="20260405005047 +0000" channel="848"><title lang="en">Rockin Robin 1-encoded2</title><category lang="en">Entertainment</category></programme>
<programme start="20260405005005 +0000" stop="20260405005305 +0000" channel="848"><title lang="en">confidential 1-encoded2</title><category lang="en">Entertainment</category></programme>
<programme start="20260405005257 +0000" stop="20260405005657 +0000" channel="848"><title lang="en">THE NIGHT CHICAGO DIED-encoded2</title><category lang="en">Entertainment</category></programme>
<programme start="20260405005647 +0000" stop="20260405005947 +0000" channel="848"><title lang="en">TVS Logo</title><category lang="en">Entertainment</category></programme>
<programme start="20260405005918 +0000" stop="20260405010618 +0000" channel="848"><title lang="en">Touch The Wind-encoded2</title><category lang="en">Entertainment</category></programme>
<programme start="20260405010548 +0000" stop="20260405010848 +0000" channel="848"><title lang="en">Turn Down Day-encoded2</title><category lang="en">Entertainment</category></programme>
<programme start="20260405010840 +0000" stop="20260405011240 +0000" channel="848"><title lang="en">THE WONDERER-encoded2</title><category lang="en">Entertainment</category></programme>
<programme start="20260405011148 +0000" stop="20260405011548 +0000" channel="848"><title lang="en">back in love again 1-encoded2</title><category lang="en">Entertainment</category></programme>
<programme start="20260405011519 +0000" stop="20260405040019 +0000" channel="848"><title lang="en">Rare Collectibles</title><category lang="en">Entertainment</category></programme>
<programme start="20260405003119 +0000" stop="20260405010019 +0000" channel="849"><title lang="en">Jack Paar Show (1954)</title><category lang="en">TV Classics</category></programme>
<programme start="20260405005938 +0000" stop="20260405020038 +0000" channel="849"><title lang="en">Texaco Star Theater with Ethel Merman</title><category lang="en">TV Classics</category></programme>
<programme start="20260405020032 +0000" stop="20260405023232 +0000" channel="849"><title lang="en">Morey Amsterdam Show with Boots Orlanis</title><category lang="en">TV Classics</category></programme>
<programme start="20260405023143 +0000" stop="20260405031643 +0000" channel="849"><title lang="en">The Buick-Berle Show with Mickey Rooney</title><category lang="en">TV Classics</category></programme>
<programme start="20260405031614 +0000" stop="20260405034714 +0000" channel="849"><title lang="en">The Ben Blue Show (1950)</title><category lang="en">TV Classics</category></programme>
<programme start="20260405034629 +0000" stop="20260405040029 +0000" channel="849"><title lang="en">Cavalcade of Stars with Jackie Robinson</title><category lang="en">TV Classics</category></programme>
<programme start="20260405003909 +0000" stop="20260405013709 +0000" channel="TVSBoxing.us@SD"><title lang="en">teleup-event_1679252400_3600</title><category lang="en">Featured</category></programme>
<programme start="20260405013657 +0000" stop="20260405023157 +0000" channel="TVSBoxing.us@SD"><title lang="en">teleup-event_1679256000_3600</title><category lang="en">Featured</category></programme>
<programme start="20260405023154 +0000" stop="20260405032454 +0000" channel="TVSBoxing.us@SD"><title lang="en">teleup-event_1679259600_3150</title><category lang="en">Featured</category></programme>
<programme start="20260405032450 +0000" stop="20260405034850 +0000" channel="TVSBoxing.us@SD"><title lang="en">teleup-event_1679228983_1409</title><category lang="en">Featured</category></programme>
<programme start="20260405034819 +0000" stop="20260405040019 +0000" channel="TVSBoxing.us@SD"><title lang="en">teleup-event_1679240408_3176</title><category lang="en">Featured</category></programme>
<programme start="20260405002323 +0000" stop="20260405011223 +0000" channel="TVSCipherNetwork.us@SD"><title lang="en">The Alfred Hitchcock Hour S03E17</title><category lang="en">TV Classics</category></programme>
<programme start="20260405011147 +0000" stop="20260405020247 +0000" channel="TVSCipherNetwork.us@SD"><title lang="en">The Alfred Hitchcock Hour S03E20</title><category lang="en">TV Classics</category></programme>
<programme start="20260405020235 +0000" stop="20260405025335 +0000" channel="TVSCipherNetwork.us@SD"><title lang="en">The Alfred Hitchcock Hour S03E22</title><category lang="en">TV Classics</category></programme>
<programme start="20260405025302 +0000" stop="20260405034002 +0000" channel="TVSCipherNetwork.us@SD"><title lang="en">The Alfred Hitchcock Hour S03E23</title><category lang="en">TV Classics</category></programme>
<programme start="20260405033935 +0000" stop="20260405034235 +0000" channel="TVSCipherNetwork.us@SD"><title lang="en">Model Girl 1-encoded2</title><category lang="en">TV Classics</category></programme>
<programme start="20260405034213 +0000" stop="20260405034613 +0000" channel="TVSCipherNetwork.us@SD"><title lang="en">betcha by golly wow 2-encoded2</title><category lang="en">TV Classics</category></programme>
<programme start="20260405034528 +0000" stop="20260405040028 +0000" channel="TVSCipherNetwork.us@SD"><title lang="en">The Alfred Hitchcock Hour S03E21</title><category lang="en">TV Classics</category></programme>
<programme start="20260405002315 +0000" stop="20260405020615 +0000" channel="TVSClassicMovies.us@SD"><title lang="en">Beneath the 12 Mile Reef</title><category lang="en">Movies</category></programme>
<programme start="20260405020610 +0000" stop="20260405020910 +0000" channel="TVSClassicMovies.us@SD"><title lang="en">AD - Tax Settlements (800) 219-8153</title><category lang="en">Movies</category></programme>
<programme start="20260405020850 +0000" stop="20260405035550 +0000" channel="TVSClassicMovies.us@SD"><title lang="en">A Connecticut Yankee In King Arthur&apos;s Court</title><category lang="en">Movies</category></programme>
<programme start="20260405035533 +0000" stop="20260405035833 +0000" channel="TVSClassicMovies.us@SD"><title lang="en">TVS Logo</title><category lang="en">Movies</category></programme>
<programme start="20260405035803 +0000" stop="20260405040003 +0000" channel="TVSClassicMovies.us@SD"><title lang="en">The Americano (1954)</title><category lang="en">Movies</category></programme>
<programme start="20260405003909 +0000" stop="20260405013709 +0000" channel="TVSClassicSports.us@SD"><title lang="en">teleup-event_1679252400_3600</title><category lang="en">Featured</category></programme>
<programme start="20260405013657 +0000" stop="20260405023157 +0000" channel="TVSClassicSports.us@SD"><title lang="en">teleup-event_1679256000_3600</title><category lang="en">Featured</category></programme>
<programme start="20260405023154 +0000" stop="20260405032454 +0000" channel="TVSClassicSports.us@SD"><title lang="en">teleup-event_1679259600_3150</title><category lang="en">Featured</category></programme>
<programme start="20260405032450 +0000" stop="20260405034850 +0000" channel="TVSClassicSports.us@SD"><title lang="en">teleup-event_1679228983_1409</title><category lang="en">Featured</category></programme>
<programme start="20260405034819 +0000" stop="20260405040019 +0000" channel="TVSClassicSports.us@SD"><title lang="en">teleup-event_1679240408_3176</title><category lang="en">Featured</category></programme>
<programme start="20260405003909 +0000" stop="20260405013709 +0000" channel="TVSComedyNetwork.us@SD"><title lang="en">teleup-event_1679252400_3600</title><category lang="en">Entertainment</category></programme>
<programme start="20260405013657 +0000" stop="20260405023157 +0000" channel="TVSComedyNetwork.us@SD"><title lang="en">teleup-event_1679256000_3600</title><category lang="en">Entertainment</category></programme>
<programme start="20260405023154 +0000" stop="20260405032454 +0000" channel="TVSComedyNetwork.us@SD"><title lang="en">teleup-event_1679259600_3150</title><category lang="en">Entertainment</category></programme>
<programme start="20260405032450 +0000" stop="20260405034850 +0000" channel="TVSComedyNetwork.us@SD"><title lang="en">teleup-event_1679228983_1409</title><category lang="en">Entertainment</category></programme>
<programme start="20260405034819 +0000" stop="20260405040019 +0000" channel="TVSComedyNetwork.us@SD"><title lang="en">teleup-event_1679240408_3176</title><category lang="en">Entertainment</category></programme>
<programme start="20260405005027 +0000" stop="20260405022227 +0000" channel="TVSDriveInMovie.us@SD"><title lang="en">The New Barbarians</title><category lang="en">Movies</category></programme>
<programme start="20260405022141 +0000" stop="20260405034241 +0000" channel="TVSDriveInMovie.us@SD"><title lang="en">Conquest of Space</title><category lang="en">Movies</category></programme>
<programme start="20260405034234 +0000" stop="20260405040034 +0000" channel="TVSDriveInMovie.us@SD"><title lang="en">Death Hunt</title><category lang="en">Movies</category></programme>
<programme start="20260405011202 +0000" stop="20260405023202 +0000" channel="TVSFilmNoirNetwork.us@SD"><title lang="en">Iron Man (1951)</title><category lang="en">Movies</category></programme>
<programme start="20260405023134 +0000" stop="20260405034934 +0000" channel="TVSFilmNoirNetwork.us@SD"><title lang="en">The Killer That Stalked New York</title><category lang="en">Movies</category></programme>
<programme start="20260405034911 +0000" stop="20260405040011 +0000" channel="TVSFilmNoirNetwork.us@SD"><title lang="en">The 39 Steps (1935)</title><category lang="en">Movies</category></programme>
<programme start="20260405002446 +0000" stop="20260405014146 +0000" channel="TVSFrontPageDetective.us@SD"><title lang="en">McMillan &amp; Wife 105</title><category lang="en">TV Classics</category></programme>
<programme start="20260405014123 +0000" stop="20260405025823 +0000" channel="TVSFrontPageDetective.us@SD"><title lang="en">McMillan &amp; Wife 101 - Murder by the Barrel</title><category lang="en">TV Classics</category></programme>
<programme start="20260405025752 +0000" stop="20260405035052 +0000" channel="TVSFrontPageDetective.us@SD"><title lang="en">Quincy ME S02E08</title><category lang="en">TV Classics</category></programme>
<programme start="20260405035045 +0000" stop="20260405040045 +0000" channel="TVSFrontPageDetective.us@SD"><title lang="en">The Fugitive Ep 1 - Fear in a Desert City</title><category lang="en">TV Classics</category></programme>
<programme start="20260405000946 +0000" stop="20260405001646 +0000" channel="TVSHiTops.us@SD"><title lang="en">Casper S01E37 Fright From Wrong</title><category lang="en">Kids &amp; Family</category></programme>
<programme start="20260405001638 +0000" stop="20260405004338 +0000" channel="TVSHiTops.us@SD"><title lang="en">Courageous Cat and Minute Mouse Vol. 10</title><category lang="en">Kids &amp; Family</category></programme>
<programme start="20260405004252 +0000" stop="20260405010452 +0000" channel="TVSHiTops.us@SD"><title lang="en">Clutch Cargo</title><category lang="en">Kids &amp; Family</category></programme>
<programme start="20260405010359 +0000" stop="20260405015159 +0000" channel="TVSHiTops.us@SD"><title lang="en">George of the Jungle - Banana Deficiency</title><category lang="en">Kids &amp; Family</category></programme>
<programme start="20260405015105 +0000" stop="20260405015605 +0000" channel="TVSHiTops.us@SD"><title lang="en">The King and Odie - Left Alone Leonardo</title><category lang="en">Kids &amp; Family</category></programme>
<programme start="20260405015545 +0000" stop="20260405022345 +0000" channel="TVSHiTops.us@SD"><title lang="en">Sky King 3</title><category lang="en">Kids &amp; Family</category></programme>
<programme start="20260405022313 +0000" stop="20260405025413 +0000" channel="TVSHiTops.us@SD"><title lang="en">Calvin And The Colonel 1</title><category lang="en">Kids &amp; Family</category></programme>
<programme start="20260405025327 +0000" stop="20260405025927 +0000" channel="TVSHiTops.us@SD"><title lang="en">Crusader Rabbit Crusade 1 Episode 03</title><category lang="en">Kids &amp; Family</category></programme>
<programme start="20260405025839 +0000" stop="20260405030739 +0000" channel="TVSHiTops.us@SD"><title lang="en">1967 Green Lantern Cartoon</title><category lang="en">Kids &amp; Family</category></programme>
<programme start="20260405030649 +0000" stop="20260405032949 +0000" channel="TVSHiTops.us@SD"><title lang="en">Doctor Dolittle - The Great Turkey Race</title><category lang="en">Kids &amp; Family</category></programme>
<programme start="20260405032936 +0000" stop="20260405040036 +0000" channel="TVSHiTops.us@SD"><title lang="en">Paul Winchell Show</title><category lang="en">Kids &amp; Family</category></programme>
<programme start="20260405003909 +0000" stop="20260405013709 +0000" channel="TVSHollywoodHistory.us@SD"><title lang="en">teleup-event_1679252400_3600</title><category lang="en">Mixed Programming</category></programme>
<programme start="20260405013657 +0000" stop="20260405023157 +0000" channel="TVSHollywoodHistory.us@SD"><title lang="en">teleup-event_1679256000_3600</title><category lang="en">Mixed Programming</category></programme>
<programme start="20260405023154 +0000" stop="20260405032454 +0000" channel="TVSHollywoodHistory.us@SD"><title lang="en">teleup-event_1679259600_3150</title><category lang="en">Mixed Programming</category></programme>
<programme start="20260405032450 +0000" stop="20260405034850 +0000" channel="TVSHollywoodHistory.us@SD"><title lang="en">teleup-event_1679228983_1409</title><category lang="en">Mixed Programming</category></programme>
<programme start="20260405034819 +0000" stop="20260405040019 +0000" channel="TVSHollywoodHistory.us@SD"><title lang="en">teleup-event_1679240408_3176</title><category lang="en">Mixed Programming</category></programme>
<programme start="20260405003909 +0000" stop="20260405013709 +0000" channel="TVSHorrorNetwork.us@SD"><title lang="en">teleup-event_1679252400_3600</title><category lang="en">Movies</category></programme>
<programme start="20260405013657 +0000" stop="20260405023157 +0000" channel="TVSHorrorNetwork.us@SD"><title lang="en">teleup-event_1679256000_3600</title><category lang="en">Movies</category></programme>
<programme start="20260405023154 +0000" stop="20260405032454 +0000" channel="TVSHorrorNetwork.us@SD"><title lang="en">teleup-event_1679259600_3150</title><category lang="en">Movies</category></programme>
<programme start="20260405032450 +0000" stop="20260405034850 +0000" channel="TVSHorrorNetwork.us@SD"><title lang="en">teleup-event_1679228983_1409</title><category lang="en">Movies</category></programme>
<programme start="20260405034819 +0000" stop="20260405040019 +0000" channel="TVSHorrorNetwork.us@SD"><title lang="en">teleup-event_1679240408_3176</title><category lang="en">Movies</category></programme>
<programme start="20260405002401 +0000" stop="20260405011401 +0000" channel="TVSMainstreet.us@SD"><title lang="en">Daniel Boone S06E26</title><category lang="en">Entertainment</category></programme>
<programme start="20260405011353 +0000" stop="20260405020353 +0000" channel="TVSMainstreet.us@SD"><title lang="en">Daniel Boone S06E24</title><category lang="en">Entertainment</category></programme>
<programme start="20260405020349 +0000" stop="20260405020649 +0000" channel="TVSMainstreet.us@SD"><title lang="en">confidential 1</title><category lang="en">Entertainment</category></programme>
<programme start="20260405020631 +0000" stop="20260405025631 +0000" channel="TVSMainstreet.us@SD"><title lang="en">Daniel Boone S06E22</title><category lang="en">Entertainment</category></programme>
<programme start="20260405025616 +0000" stop="20260405031116 +0000" channel="TVSMainstreet.us@SD"><title lang="en">Tim McCoy 01</title><category lang="en">Entertainment</category></programme>
<programme start="20260405031043 +0000" stop="20260405031443 +0000" channel="TVSMainstreet.us@SD"><title lang="en">96 tears11</title><category lang="en">Entertainment</category></programme>
<programme start="20260405031419 +0000" stop="20260405034019 +0000" channel="TVSMainstreet.us@SD"><title lang="en">US Marshall 2</title><category lang="en">Entertainment</category></programme>
<programme start="20260405034011 +0000" stop="20260405040011 +0000" channel="TVSMainstreet.us@SD"><title lang="en">US Marshall 3</title><category lang="en">Entertainment</category></programme>
<programme start="20260405003822 +0000" stop="20260405012622 +0000" channel="TVSNostalgia.us@SD"><title lang="en">The Alfred Hitchcock Hour S03E29</title><category lang="en">TV Classics</category></programme>
<programme start="20260405012555 +0000" stop="20260405021655 +0000" channel="TVSNostalgia.us@SD"><title lang="en">The Alfred Hitchcock Hour S03E22</title><category lang="en">TV Classics</category></programme>
<programme start="20260405021622 +0000" stop="20260405024422 +0000" channel="TVSNostalgia.us@SD"><title lang="en">Suspense</title><category lang="en">TV Classics</category></programme>
<programme start="20260405024412 +0000" stop="20260405032812 +0000" channel="TVSNostalgia.us@SD"><title lang="en">The Alfred Hitchcock Hour S02E14</title><category lang="en">TV Classics</category></programme>
<programme start="20260405032809 +0000" stop="20260405033109 +0000" channel="TVSNostalgia.us@SD"><title lang="en">TVS Logo</title><category lang="en">TV Classics</category></programme>
<programme start="20260405033047 +0000" stop="20260405040047 +0000" channel="TVSNostalgia.us@SD"><title lang="en">Burke&apos;s Law</title><category lang="en">TV Classics</category></programme>
<programme start="20260405011454 +0000" stop="20260405024754 +0000" channel="TVSNostalgiaMovies.us@SD"><title lang="en">Mr. Arkadin</title><category lang="en">Movies</category></programme>
<programme start="20260405024731 +0000" stop="20260405040031 +0000" channel="TVSNostalgiaMovies.us@SD"><title lang="en">A Blueprint for Murder</title><category lang="en">Movies</category></programme>
<programme start="20260405000440 +0000" stop="20260405003140 +0000" channel="TVSPinballNetwork.us@SD"><title lang="en">Courageous Cat and Minute Mous e Volume 07</title><category lang="en">Featured</category></programme>
<programme start="20260405003112 +0000" stop="20260405003812 +0000" channel="TVSPinballNetwork.us@SD"><title lang="en">The Pink Panther in Bully for Pink</title><category lang="en">Featured</category></programme>
<programme start="20260405003719 +0000" stop="20260405010019 +0000" channel="TVSPinballNetwork.us@SD"><title lang="en">Rocky and Bullwinkle S04E16</title><category lang="en">Featured</category></programme>
<programme start="20260405010012 +0000" stop="20260405022312 +0000" channel="TVSPinballNetwork.us@SD"><title lang="en">All Dogs Go To Heaven 2 (1996)</title><category lang="en">Featured</category></programme>
<programme start="20260405022310 +0000" stop="20260405023010 +0000" channel="TVSPinballNetwork.us@SD"><title lang="en">The Wacky Weed Andy Panda Cartoon</title><category lang="en">Featured</category></programme>
<programme start="20260405022944 +0000" stop="20260405023744 +0000" channel="TVSPinballNetwork.us@SD"><title lang="en">Hawkman</title><category lang="en">Featured</category></programme>
<programme start="20260405023707 +0000" stop="20260405025407 +0000" channel="TVSPinballNetwork.us@SD"><title lang="en">Sub-Mariner</title><category lang="en">Featured</category></programme>
<programme start="20260405025401 +0000" stop="20260405030101 +0000" channel="TVSPinballNetwork.us@SD"><title lang="en">The Pink Panther in A Fly in the Pink</title><category lang="en">Featured</category></programme>
<programme start="20260405030029 +0000" stop="20260405030329 +0000" channel="TVSPinballNetwork.us@SD"><title lang="en">TVS Logo</title><category lang="en">Featured</category></programme>
<programme start="20260405030302 +0000" stop="20260405030702 +0000" channel="TVSPinballNetwork.us@SD"><title lang="en">long tall-encoded2</title><category lang="en">Featured</category></programme>
<programme start="20260405030613 +0000" stop="20260405031213 +0000" channel="TVSPinballNetwork.us@SD"><title lang="en">Laurel And Hardy Cartoon</title><category lang="en">Featured</category></programme>
<programme start="20260405031117 +0000" stop="20260405031517 +0000" channel="TVSPinballNetwork.us@SD"><title lang="en">The New 3 Stooges</title><category lang="en">Featured</category></programme>
<programme start="20260405031442 +0000" stop="20260405032142 +0000" channel="TVSPinballNetwork.us@SD"><title lang="en">The Pink Panther</title><category lang="en">Featured</category></programme>
<programme start="20260405032104 +0000" stop="20260405032804 +0000" channel="TVSPinballNetwork.us@SD"><title lang="en">Tijuana Toads</title><category lang="en">Featured</category></programme>
<programme start="20260405032718 +0000" stop="20260405034018 +0000" channel="TVSPinballNetwork.us@SD"><title lang="en">Tom Terrific</title><category lang="en">Featured</category></programme>
<programme start="20260405033919 +0000" stop="20260405040019 +0000" channel="TVSPinballNetwork.us@SD"><title lang="en">Matty&apos;s Funnies with Beany and Cecil</title><category lang="en">Featured</category></programme>
<programme start="20260405003909 +0000" stop="20260405013709 +0000" channel="TVSQuizShowNetwork.us@SD"><title lang="en">teleup-event_1679252400_3600</title><category lang="en">Kids &amp; Family</category></programme>
<programme start="20260405013657 +0000" stop="20260405023157 +0000" channel="TVSQuizShowNetwork.us@SD"><title lang="en">teleup-event_1679256000_3600</title><category lang="en">Kids &amp; Family</category></programme>
<programme start="20260405023154 +0000" stop="20260405032454 +0000" channel="TVSQuizShowNetwork.us@SD"><title lang="en">teleup-event_1679259600_3150</title><category lang="en">Kids &amp; Family</category></programme>
<programme start="20260405032450 +0000" stop="20260405034850 +0000" channel="TVSQuizShowNetwork.us@SD"><title lang="en">teleup-event_1679228983_1409</title><category lang="en">Kids &amp; Family</category></programme>
<programme start="20260405034819 +0000" stop="20260405040019 +0000" channel="TVSQuizShowNetwork.us@SD"><title lang="en">teleup-event_1679240408_3176</title><category lang="en">Kids &amp; Family</category></programme>
<programme start="20260405003909 +0000" stop="20260405013709 +0000" channel="TVSSelectNetwork.us@SD"><title lang="en">teleup-event_1679252400_3600</title><category lang="en">Mixed Programming</category></programme>
<programme start="20260405013657 +0000" stop="20260405023157 +0000" channel="TVSSelectNetwork.us@SD"><title lang="en">teleup-event_1679256000_3600</title><category lang="en">Mixed Programming</category></programme>
<programme start="20260405023154 +0000" stop="20260405032454 +0000" channel="TVSSelectNetwork.us@SD"><title lang="en">teleup-event_1679259600_3150</title><category lang="en">Mixed Programming</category></programme>
<programme start="20260405032450 +0000" stop="20260405034850 +0000" channel="TVSSelectNetwork.us@SD"><title lang="en">teleup-event_1679228983_1409</title><category lang="en">Mixed Programming</category></programme>
<programme start="20260405034819 +0000" stop="20260405040019 +0000" channel="TVSSelectNetwork.us@SD"><title lang="en">teleup-event_1679240408_3176</title><category lang="en">Mixed Programming</category></programme>
<programme start="20260405003909 +0000" stop="20260405013709 +0000" channel="TVSSiloDiscountNetwork.us@SD"><title lang="en">teleup-event_1679252400_3600</title><category lang="en">Kids &amp; Family</category></programme>
<programme start="20260405013657 +0000" stop="20260405023157 +0000" channel="TVSSiloDiscountNetwork.us@SD"><title lang="en">teleup-event_1679256000_3600</title><category lang="en">Kids &amp; Family</category></programme>
<programme start="20260405023154 +0000" stop="20260405032454 +0000" channel="TVSSiloDiscountNetwork.us@SD"><title lang="en">teleup-event_1679259600_3150</title><category lang="en">Kids &amp; Family</category></programme>
<programme start="20260405032450 +0000" stop="20260405034850 +0000" channel="TVSSiloDiscountNetwork.us@SD"><title lang="en">teleup-event_1679228983_1409</title><category lang="en">Kids &amp; Family</category></programme>
<programme start="20260405034819 +0000" stop="20260405040019 +0000" channel="TVSSiloDiscountNetwork.us@SD"><title lang="en">teleup-event_1679240408_3176</title><category lang="en">Kids &amp; Family</category></programme>
<programme start="20260405003909 +0000" stop="20260405013709 +0000" channel="TVSTallyHo.us@SD"><title lang="en">teleup-event_1679252400_3600</title><category lang="en">Entertainment</category></programme>
<programme start="20260405013657 +0000" stop="20260405023157 +0000" channel="TVSTallyHo.us@SD"><title lang="en">teleup-event_1679256000_3600</title><category lang="en">Entertainment</category></programme>
<programme start="20260405023154 +0000" stop="20260405032454 +0000" channel="TVSTallyHo.us@SD"><title lang="en">teleup-event_1679259600_3150</title><category lang="en">Entertainment</category></programme>
<programme start="20260405032450 +0000" stop="20260405034850 +0000" channel="TVSTallyHo.us@SD"><title lang="en">teleup-event_1679228983_1409</title><category lang="en">Entertainment</category></programme>
<programme start="20260405034819 +0000" stop="20260405040019 +0000" channel="TVSTallyHo.us@SD"><title lang="en">teleup-event_1679240408_3176</title><category lang="en">Entertainment</category></programme>
<programme start="20260405005701 +0000" stop="20260405010101 +0000" channel="TVSTavern.us@SD"><title lang="en">Casablanca 4</title><category lang="en">Featured</category></programme>
<programme start="20260405010101 +0000" stop="20260405010601 +0000" channel="TVSTavern.us@SD"><title lang="en">Casablanca 5</title><category lang="en">Featured</category></programme>
<programme start="20260405010512 +0000" stop="20260405011012 +0000" channel="TVSTavern.us@SD"><title lang="en">Lake Tahoe 2</title><category lang="en">Featured</category></programme>
<programme start="20260405010932 +0000" stop="20260405021532 +0000" channel="TVSTavern.us@SD"><title lang="en">Bowling1-encoded2</title><category lang="en">Featured</category></programme>
<programme start="20260405021529 +0000" stop="20260405023129 +0000" channel="TVSTavern.us@SD"><title lang="en">Darryl Fuller vs Gary Hinton 02</title><category lang="en">Featured</category></programme>
<programme start="20260405023034 +0000" stop="20260405033434 +0000" channel="TVSTavern.us@SD"><title lang="en">BOWLING 2-encoded2</title><category lang="en">Featured</category></programme>
<programme start="20260405033407 +0000" stop="20260405040007 +0000" channel="TVSTavern.us@SD"><title lang="en">rollerskating5-encoded2</title><category lang="en">Featured</category></programme>
<programme start="20260405001915 +0000" stop="20260405004815 +0000" channel="TVSTodayHomeEntertainmentNetwork.us@SD"><title lang="en">Ninja Foodi Grill (800) 383-3597</title><category lang="en">Mixed Programming</category></programme>
<programme start="20260405004757 +0000" stop="20260405005057 +0000" channel="TVSTodayHomeEntertainmentNetwork.us@SD"><title lang="en">May I-encoded2</title><category lang="en">Mixed Programming</category></programme>
<programme start="20260405005032 +0000" stop="20260405011232 +0000" channel="TVSTodayHomeEntertainmentNetwork.us@SD"><title lang="en">Mari S01e02r - Laila Ali &amp; High Five</title><category lang="en">Mixed Programming</category></programme>
<programme start="20260405011151 +0000" stop="20260405013151 +0000" channel="TVSTodayHomeEntertainmentNetwork.us@SD"><title lang="en">Mari S01e03r - Taste &amp; Gabe Rosado</title><category lang="en">Mixed Programming</category></programme>
<programme start="20260405013143 +0000" stop="20260405013443 +0000" channel="TVSTodayHomeEntertainmentNetwork.us@SD"><title lang="en">THE WONDERER-encoded2</title><category lang="en">Mixed Programming</category></programme>
<programme start="20260405013441 +0000" stop="20260405020041 +0000" channel="TVSTodayHomeEntertainmentNetwork.us@SD"><title lang="en">Mari S01e01r - Combinations &amp; Nancy Rodriguez</title><category lang="en">Mixed Programming</category></programme>
<programme start="20260405020030 +0000" stop="20260405020330 +0000" channel="TVSTodayHomeEntertainmentNetwork.us@SD"><title lang="en">Just like Romeo and Juliet Instrumental-encoded2</title><category lang="en">Mixed Programming</category></programme>
<programme start="20260405020318 +0000" stop="20260405023218 +0000" channel="TVSTodayHomeEntertainmentNetwork.us@SD"><title lang="en">Paint Zoom (800) 598-0578</title><category lang="en">Mixed Programming</category></programme>
<programme start="20260405023210 +0000" stop="20260405023510 +0000" channel="TVSTodayHomeEntertainmentNetwork.us@SD"><title lang="en">she&apos;s everything i wanted you to be-encoded2</title><category lang="en">Mixed Programming</category></programme>
<programme start="20260405023442 +0000" stop="20260405023842 +0000" channel="TVSTodayHomeEntertainmentNetwork.us@SD"><title lang="en">long tall-encoded2</title><category lang="en">Mixed Programming</category></programme>
<programme start="20260405023753 +0000" stop="20260405030453 +0000" channel="TVSTodayHomeEntertainmentNetwork.us@SD"><title lang="en">Mari s01e04 - Cyborg, Corey, Philadelphian</title><category lang="en">Mixed Programming</category></programme>
<programme start="20260405030420 +0000" stop="20260405033320 +0000" channel="TVSTodayHomeEntertainmentNetwork.us@SD"><title lang="en">Ninja Foodi Grill (800) 383-3597</title><category lang="en">Mixed Programming</category></programme>
<programme start="20260405033302 +0000" stop="20260405033602 +0000" channel="TVSTodayHomeEntertainmentNetwork.us@SD"><title lang="en">May I-encoded2</title><category lang="en">Mixed Programming</category></programme>
<programme start="20260405033537 +0000" stop="20260405035737 +0000" channel="TVSTodayHomeEntertainmentNetwork.us@SD"><title lang="en">Mari S01e02r - Laila Ali &amp; High Five</title><category lang="en">Mixed Programming</category></programme>
<programme start="20260405035656 +0000" stop="20260405040056 +0000" channel="TVSTodayHomeEntertainmentNetwork.us@SD"><title lang="en">Mari S01e03r - Taste &amp; Gabe Rosado</title><category lang="en">Mixed Programming</category></programme>
<programme start="20260405003909 +0000" stop="20260405013709 +0000" channel="TVSTurbo.us@SD"><title lang="en">teleup-event_1679252400_3600</title><category lang="en">Sports</category></programme>
<programme start="20260405013657 +0000" stop="20260405023157 +0000" channel="TVSTurbo.us@SD"><title lang="en">teleup-event_1679256000_3600</title><category lang="en">Sports</category></programme>
<programme start="20260405023154 +0000" stop="20260405032454 +0000" channel="TVSTurbo.us@SD"><title lang="en">teleup-event_1679259600_3150</title><category lang="en">Sports</category></programme>
<programme start="20260405032450 +0000" stop="20260405034850 +0000" channel="TVSTurbo.us@SD"><title lang="en">teleup-event_1679228983_1409</title><category lang="en">Sports</category></programme>
<programme start="20260405034819 +0000" stop="20260405040019 +0000" channel="TVSTurbo.us@SD"><title lang="en">teleup-event_1679240408_3176</title><category lang="en">Sports</category></programme>
<programme start="20260405003912 +0000" stop="20260405025112 +0000" channel="TVSWesternMovie.us@SD"><title lang="en">Bite the Bullet</title><category lang="en">Movies</category></programme>
<programme start="20260405025022 +0000" stop="20260405040022 +0000" channel="TVSWesternMovie.us@SD"><title lang="en">Navajo</title><category lang="en">Movies</category></programme>
<programme start="20260405003909 +0000" stop="20260405013709 +0000" channel="TVSWomenSports.us@SD"><title lang="en">teleup-event_1679252400_3600</title><category lang="en">Sports</category></programme>
<programme start="20260405013657 +0000" stop="20260405023157 +0000" channel="TVSWomenSports.us@SD"><title lang="en">teleup-event_1679256000_3600</title><category lang="en">Sports</category></programme>
<programme start="20260405023154 +0000" stop="20260405032454 +0000" channel="TVSWomenSports.us@SD"><title lang="en">teleup-event_1679259600_3150</title><category lang="en">Sports</category></programme>
<programme start="20260405032450 +0000" stop="20260405034850 +0000" channel="TVSWomenSports.us@SD"><title lang="en">teleup-event_1679228983_1409</title><category lang="en">Sports</category></programme>
<programme start="20260405034819 +0000" stop="20260405040019 +0000" channel="TVSWomenSports.us@SD"><title lang="en">teleup-event_1679240408_3176</title><category lang="en">Sports</category></programme>
</tv>